.gitignore
CHANGES.txt
MANIFEST.in
README.rst
bootstrap.py
buildout.cfg
jenkins.cfg
setup.py
collective/__init__.py
collective.checktranslated.egg-info/PKG-INFO
collective.checktranslated.egg-info/SOURCES.txt
collective.checktranslated.egg-info/dependency_links.txt
collective.checktranslated.egg-info/entry_points.txt
collective.checktranslated.egg-info/namespace_packages.txt
collective.checktranslated.egg-info/not-zip-safe
collective.checktranslated.egg-info/requires.txt
collective.checktranslated.egg-info/top_level.txt
collective/checktranslated/__init__.py
collective/checktranslated/configure.zcml
collective/checktranslated/setuphandlers.py
collective/checktranslated/symptoms.py
collective/checktranslated/testing.py
collective/checktranslated/locales/collective.jekyll.pot
collective/checktranslated/locales/en/LC_MESSAGES/collective.jekyll.po
collective/checktranslated/locales/fr/LC_MESSAGES/collective.jekyll.po
collective/checktranslated/locales/nl/LC_MESSAGES/collective.jekyll.po
collective/checktranslated/profiles/default/collective_checktranslated_various.txt
collective/checktranslated/profiles/default/metadata.xml
collective/checktranslated/tests/__init__.py
collective/checktranslated/tests/test_translated.py
docs/INSTALL.txt
docs/LICENSE.GPL
docs/LICENSE.txt