Metadata-Version: 1.1
Name: collective.checktranslated
Version: 1.0.1
Summary: This products make a table with all your content and their translation.
Home-page: https://github.com/CIRB/collective.checktranslated
Author: Benoit SUTTOR
Author-email: bsuttor@cirb.irisnet.be
License: GPL
Platform: UNKNOWN
Classifier: Framework :: Plone
Classifier: Programming Language :: Python
